{
    "harmoniums": [
      {
        "name": "Harmonium",
        "builder": "Jan Tuček",
        "type":"tlakový",
        "model": "Classic 10",
        "dating": "1895 - 1901",
        "placeOfManufacture": "Kutná Hora",
        "owner": "Historická sbírka",
        "id": "in. Č. 001",
        "location":"expozice půda",
        "description": "Jednomanuálové harmonium s 4 rejstříky, známé svou jemnou intonací.",
        "locationFind": "Česká republika",
        "signMakers": "Jan Tuček - Kutná Hora",
        "size": {
          "height": "112",
          "width": "90",
          "depth": "60"
        },
        "materials": ["dřevo", "mosaz", "kůže"],
        "manuals":"1",
        "pedal": "ne",
        "disposition": {
          "bas": ["Violon Bass"],
          "treble": ["Flétna", "Salicionál"],
          "pedal": [],
          "couplings": []
        },
        "pictures": ["public/harmoniums/harmonium_1.jpg", "public/harmoniums/harmonium_2.jpg", "public/harmoniums/harmonium_3.jpg", "public/harmoniums/harmonium_4.jpg"]
      },
      {
        "name": "Fisharmonium",
        "builder": "Alois Hugo Lhota",
        "type":"tlakový",
        "model": "Concert Master",
        "dating": "1888 - 1894",
        "placeOfManufacture": "Hradec Králové",
        "owner": "Soukromá sbírka",
        "id": "in. Č. 002",
        "location":"depozitář",
        "description": "Dvoumánuálové harmonium s pedálem a 8 rejstříky, vhodné pro koncertní účely.",
        "locationFind": "Hradec Králové",
        "signMakers": "Alois Hugo Lhota - Hradec Králové",
        "size": {
          "height": "105",
          "width": "89",
          "depth": "55"
        },
        "materials": ["dřevo", "mosaz", "kůže"],
        "manuals":"1",
        "pedal": "ano",
        "disposition": {
          "bas": ["Bourdon", "Violon"],
          "treble": ["Principal", "Gamba", "Clarinet"],
          "pedal": ["Subbass"],
          "couplings": ["Manuál I/II"]
        },
        "pictures": ["public/harmoniums/harmonium_5.jpg"]
      },
      {
        "name": "Reed Organ",
        "builder": "John Estey",
        "type":"sací",
        "model": "Chapel 20",
        "dating": "1887 - 1892",
        "placeOfManufacture": "USA",
        "owner": "Kaple sv. Petra",
        "id": "in. Č. 003",
        "location":"expozice půda",
        "description": "Velké dvoumánuálové harmonium s pedálem a 12 rejstříky, oblíbené pro chrámové použití.",
        "locationFind": "USA",
        "signMakers": "John Estey - Philadelphia",
        "size": {
          "height": "102",
          "width": "120",
          "depth": "65"
        },
        "materials": ["dřevo", "mosaz", "ocel"],
        "manuals":"2",
        "pedal": "ano",
        "disposition": {
          "bas": ["Principal Bass", "Octave"],
          "treble": ["Flétna", "Oboe", "Trumpet"],
          "pedal": ["Pedal Bass"],
          "couplings": ["Bas/Diskant", "Manuál I/II"]
        },
        "pictures": ["public/harmoniums/harmonium_3.jpg"]
      },
      {
        "name": "Jazyčkové Varhany",
        "builder": "Packart",
        "type":"sací",
        "model": "Orchestra Grande",
        "dating": "1885- 1890",
        "placeOfManufacture": "USA",
        "owner": "Muzeum Hudby",
        "id": "in. Č. 004",
        "location":"expozice půda",
        "description": "Jednomanuálové harmonium s 5 rejstříky a silným basem.",
        "locationFind": "Německo",
        "signMakers": "Packart - USA",
        "size": {
          "height": "110",
          "width": "103",
          "depth": "55"
        },
        "materials": ["dřevo", "mosaz", "kůže"],
        "manuals":"1",
        "pedal": "ne",
        "disposition": {
          "bas": ["Subbass", "Principal Bass"],
          "treble": ["Flétna"],
          "pedal": [],
          "couplings": []
        },
        "pictures": ["public/harmoniums/harmonium_4.jpg"]
      },
      {
        "name": "Harmonium",
        "builder": "Debain",
        "type":"tlakový",
        "model": "Concert Organ",
        "dating": "1866",
        "placeOfManufacture": "Francie",
        "owner": "Muzeum Harmonium",
        "id": "in. Č. 005",
        "location":"expozice půda",
        "description": "Velké harmonium s dvěma manuály, 15 rejstříky a pedálem, vhodné pro koncertní sály.",
        "locationFind": "Paříž",
        "signMakers": "Debain - Paříž",
        "size": {
          "height": "100",
          "width": "88",
          "depth": "65"
        },
        "materials": ["dřevo", "ocel", "kůže"],
        "manuals":"1",
        "pedal": "ne",
        "disposition": {
          "bas": ["Bourdon", "Violon", "Principal Bass"],
          "treble": ["Gamba", "Flétna", "Oboe", "Clarinet"],
          "pedal": [],
          "couplings": []
        },
        "pictures": ["public/harmoniums/harmonium_2.jpg"]
      },
      {
        "name": "Fisharmonium",
        "builder": "Petrof",
        "type":"tlakový",
        "model": "Classic 5",
        "dating": "1920 - 1930",
        "placeOfManufacture": "Hradec Králové",
        "owner": "Soukromý sběratel",
        "id": "in. Č. 006",
        "location":"depozitář",
        "description": "Jednomanuálové harmonium s 3 rejstříky, oblíbené pro domácí použití.",
        "locationFind": "Hradec Králové",
        "signMakers": "Petrof - Hradec Králové",
        "size": {
          "height": "102",
          "width": "85",
          "depth": "55"
        },
        "materials": ["dřevo", "slonová kost", "kůže"],
        "manuals":"1",
        "pedal": "ne",
        "disposition": {
          "bas": ["Violon Bass"],
          "treble": ["Flétna", "Salicionál"],
          "pedal": [],
          "couplings": []
        },
        "pictures": ["public/harmoniums/harmonium_1.jpg"]
      },
      {
        "name": "Harmonium",
        "builder": "Jan Tuček",
        "type":"tlakový",
        "model": "Classic 10",
        "dating": "1906 - 1910",
        "placeOfManufacture": "Kutná Hora",
        "owner": "Historická sbírka",
        "id": "in. Č. 007",
        "location":"expozice půda",
        "description": "Jednomanuálové harmonium s 4 rejstříky, známé svou jemnou intonací.",
        "locationFind": "Česká republika",
        "signMakers": "Jan Tuček - Kutná Hora",
        "size": {
          "height": "102",
          "width": "86",
          "depth": "58"
        },
        "materials": ["dřevo", "mosaz", "kůže"],
        "manuals":"1",
        "pedal": "ne",
        "disposition": {
          "bas": ["Violon Bass"],
          "treble": ["Flétna", "Salicionál"],
          "pedal": [],
          "couplings": []
        },
        "pictures": ["public/harmoniums/harmonium_4.jpg"]
      },
      {
        "name": "Fisharmonium",
        "builder": "Alois Hugo Lhota",
        "type":"tlakový",
        "model": "Concert Master",
        "dating": "1890 - 1900",
        "placeOfManufacture": "Hradec Králové",
        "owner": "Soukromá sbírka",
        "id": "in. Č. 008",
        "location":"expozice půda",
        "description": "Dvoumánuálové harmonium s pedálem a 8 rejstříky, vhodné pro koncertní účely.",
        "locationFind": "Hradec Králové",
        "signMakers": "Alois Hugo Lhota - Hradec Králové",
        "size": {
          "height": "120",
          "width": "115",
          "depth": "70"
        },
        "materials": ["dřevo", "mosaz", "kůže"],
        "manuals":"1",
        "pedal": "ano",
        "disposition": {
          "bas": ["Bourdon", "Violon"],
          "treble": ["Principal", "Gamba", "Clarinet"],
          "pedal": ["Subbass"],
          "couplings": ["Manuál I/II"]
        },
        "pictures": ["public/harmoniums/harmonium_5.jpg"]
      },
      {
        "name": "Reed Organ",
        "builder": "John Estey",
        "type":"sací",
        "model": "Chapel 20",
        "dating": "1895 - 1897",
        "placeOfManufacture": "USA",
        "owner": "Kaple sv. Petra",
        "id": "in. Č. 009",
        "location":"depozitář",
        "description": "Velké dvoumánuálové harmonium s pedálem a 12 rejstříky, oblíbené pro chrámové použití.",
        "locationFind": "USA",
        "signMakers": "John Estey - Philadelphia",
        "size": {
          "height": "112",
          "width": "90",
          "depth": "60"
        },
        "materials": ["dřevo", "mosaz", "ocel"],
        "manuals":"1",
        "pedal": "ano",
        "disposition": {
          "bas": ["Principal Bass", "Octave"],
          "treble": ["Flétna", "Oboe", "Trumpet"],
          "pedal": ["Pedal Bass"],
          "couplings": ["Bas/Diskant", "Manuál I/II"]
        },
        "pictures": ["public/harmoniums/harmonium_4.jpg"]
      },
      {
        "name": "Jazyčkové Varhany",
        "builder": "Packart",
        "type":"sací",
        "model": "Orchestra Grande",
        "dating": "1888 - 1895",
        "placeOfManufacture": "USA",
        "owner": "Muzeum Hudby",
        "id": "in. Č. 010",
        "location":"expozice půda",
        "description": "Jednomanuálové harmonium s 5 rejstříky a silným basem.",
        "locationFind": "Německo",
        "signMakers": "Packart - USA",
        "size": {
          "height": "112",
          "width": "90",
          "depth": "60"
        },
        "materials": ["dřevo", "mosaz", "kůže"],
        "manuals":"1",
        "pedal": "ne",
        "disposition": {
          "bas": ["Subbass", "Principal Bass"],
          "treble": ["Flétna"],
          "pedal": [],
          "couplings": []
        },
        "pictures": ["public/harmoniums/harmonium_1.jpg"]
      },
      {
        "name": "Harmonium",
        "builder": "Tuček",
        "type":"tlakový",
        "model": "Concert Organ",
        "dating": "1865 - 1870",
        "placeOfManufacture": "Kutná Hora",
        "owner": "Muzeum Harmonium",
        "id": "in. Č. 011",
        "location":"expozice půda",
        "description": "Velké harmonium s dvěma manuály, 15 rejstříky a pedálem, vhodné pro koncertní sály.",
        "locationFind": "Paříž",
        "signMakers": "Jan Tuček - Kutná Hora",
        "size": {
          "height": "112",
          "width": "90",
          "depth": "60"
        },
        "materials": ["dřevo", "ocel", "kůže"],
        "manuals":"2",
        "pedal": "ano",
        "disposition": {
          "bas": ["Bourdon", "Violon", "Principal Bass"],
          "treble": ["Gamba", "Flétna", "Oboe", "Clarinet"],
          "pedal": ["Pedal Bass", "Pedal Octave"],
          "couplings": ["Manuál I/II"]
        },
        "pictures": ["public/harmoniums/harmonium_3.jpg"]
      },
      {
        "name": "Fisharmonium",
        "builder": "Petrof",
        "type":"sací",
        "model": "Classic 5",
        "dating": "1930 - 1940",
        "placeOfManufacture": "Hradec Králové",
        "owner": "Soukromý sběratel",
        "id": "in. Č. 012",
        "location":"depozitář",
        "description": "Jednomanuálové harmonium s 3 rejstříky, oblíbené pro domácí použití.",
        "locationFind": "Hradec Králové",
        "signMakers": "Petrof - Hradec Králové",
        "size": {
          "height": "112",
          "width": "90",
          "depth": "60"
        },
        "materials": ["dřevo", "slonová kost", "kůže"],
        "manuals":"1",
        "pedal": "ne",
        "disposition": {
          "bas": ["Violon Bass"],
          "treble": ["Flétna", "Salicionál"],
          "pedal": [],
          "couplings": []
        },
        "pictures": ["public/harmoniums/harmonium_2.jpg"]
      }
    ]
  }